pollock/__init__.py
pollock/analysis.py
pollock/dataloaders.py
pollock/explain.py
pollock/model.py
pollock/pollock.R
pollock/pollock.py
pollock/pollock_setup.py
pollock/utils.py
pollock/models/__init__.py
pollock/models/analysis.py
pollock/models/explain.py
pollock/models/model.py
pollock/preprocessing/__init__.py
pollock/preprocessing/preprocessing.py
pollock/wrappers/__init__.py
pollock/wrappers/encoder_shaps.py
pollock/wrappers/explain_rds.R
pollock/wrappers/h5ad_to_rds.R
pollock/wrappers/predict_rds.R
pollock/wrappers/rds_to_h5ad.R
pollock/wrappers/rwrappers.py
pollock/wrappers/train_rds.R
dinglab_pollock-0.2.1.dist-info/LICENSE
dinglab_pollock-0.2.1.dist-info/METADATA
dinglab_pollock-0.2.1.dist-info/WHEEL
dinglab_pollock-0.2.1.dist-info/entry_points.txt
dinglab_pollock-0.2.1.dist-info/top_level.txt
dinglab_pollock-0.2.1.dist-info/RECORD
