Metadata-Version: 2.1
Name: dinglab-pollock
Version: 0.2.1
Summary: A tool for single cell classification and characterization.
Home-page: https://github.com/ding-lab/pollock
Author: Ding Lab
Author-email: estorrs@wustl.edu
License: UNKNOWN
Keywords: single cell classification expression machine learning deep learning
Platform: UNKNOWN
Classifier: License :: OSI Approved :: MIT License
Classifier: Programming Language :: Python :: 3.6
Classifier: Programming Language :: Python :: 3.7
Classifier: Programming Language :: Python :: 3.8
Requires-Python: >=3.6
License-File: LICENSE
